dq_test.py
indp_fun.py
test_fun.py
dq_test-0.2.dist-info/METADATA
dq_test-0.2.dist-info/WHEEL
dq_test-0.2.dist-info/top_level.txt
dq_test-0.2.dist-info/RECORD
